argos/__init__.py
argos/application.py
argos/info.py
argos/main.py
argos/collect/__init__.py
argos/collect/collector.py
argos/collect/collectortree.py
argos/config/__init__.py
argos/config/abstractcti.py
argos/config/boolcti.py
argos/config/choicecti.py
argos/config/configitemdelegate.py
argos/config/configtreemodel.py
argos/config/configtreeview.py
argos/config/floatcti.py
argos/config/groupcti.py
argos/config/intcti.py
argos/config/qtctis.py
argos/config/stringcti.py
argos/config/untypedcti.py
argos/external/__init__.py
argos/external/ez_setup.py
argos/external/six.py
argos/img/snipicons/README.txt
argos/img/snipicons/align-left.svg
argos/img/snipicons/asterisk.svg
argos/img/snipicons/exclamation-sign.svg
argos/img/snipicons/file-inverse.svg
argos/img/snipicons/file.svg
argos/img/snipicons/folder-close.svg
argos/img/snipicons/folder-open.svg
argos/img/snipicons/leaf.svg
argos/img/snipicons/list.svg
argos/img/snipicons/move.svg
argos/img/snipicons/reset-l.svg
argos/img/snipicons/th-large.svg
argos/img/snipicons/th-list.svg
argos/img/snipicons/warning-sign.svg
argos/inspector/__init__.py
argos/inspector/abstract.py
argos/inspector/debug.py
argos/inspector/dialog.py
argos/inspector/registry.py
argos/inspector/selectionpane.py
argos/inspector/pgplugins/__init__.py
argos/inspector/pgplugins/healpix.py
argos/inspector/pgplugins/imageplot2d.py
argos/inspector/pgplugins/lineplot1d.py
argos/inspector/pgplugins/pgctis.py
argos/inspector/pgplugins/pghistlutitem.py
argos/inspector/pgplugins/pgplotitem.py
argos/inspector/qtplugins/__init__.py
argos/inspector/qtplugins/table.py
argos/inspector/qtplugins/text.py
argos/qt/__init__.py
argos/qt/bindings.py
argos/qt/labeledwidget.py
argos/qt/misc.py
argos/qt/registry.py
argos/qt/registrytable.py
argos/qt/scientificspinbox.py
argos/qt/togglecolumn.py
argos/qt/treeitems.py
argos/qt/treemodels.py
argos/repo/__init__.py
argos/repo/baserti.py
argos/repo/detailpanes.py
argosge-0.2.1.dev1.dist-info/DESCRIPTION.rst
argosge-0.2.1.dev1.dist-info/METADATA
argosge-0.2.1.dev1.dist-info/RECORD
argosge-0.2.1.dev1.dist-info/WHEEL
argosge-0.2.1.dev1.dist-info/entry_points.txt
argosge-0.2.1.dev1.dist-info/metadata.json
argosge-0.2.1.dev1.dist-info/top_level.txt
